{
	"info": {
		"_postman_id": "7b0ace4c-ab31-4791-95cd-4afcae83e2bb",
		"name": "Image Object Detector API",
		"schema": "https://schema.getpostman.com/json/collection/v2.1.0/collection.json",
		"_exporter_id": "5645252"
	},
	"item": [
		{
			"name": "Get All Images",
			"request": {
				"method": "GET",
				"header": [],
				"url": {
					"raw": "http://localhost:3000/images?objects=dog,cat",
					"protocol": "http",
					"host": [
						"localhost"
					],
					"port": "3000",
					"path": [
						"images"
					],
					"query": [
						{
							"key": "objects",
							"value": "dog,cat"
						}
					]
				}
			},
			"response": []
		},
		{
			"name": "Get Image By Id",
			"request": {
				"method": "GET",
				"header": [],
				"url": {
					"raw": "http://localhost:3000/images/{{imageId}}",
					"protocol": "http",
					"host": [
						"localhost"
					],
					"port": "3000",
					"path": [
						"images",
						"{{imageId}}"
					]
				}
			},
			"response": []
		},
		{
			"name": "Add Image",
			"request": {
				"auth": {
					"type": "basic",
					"basic": [
						{
							"key": "password",
							"value": "{{apiSecret}}",
							"type": "string"
						},
						{
							"key": "username",
							"value": "{{apiKey}}",
							"type": "string"
						}
					]
				},
				"method": "POST",
				"header": [],
				"body": {
					"mode": "raw",
					"raw": "{\r\n    \"imgUrl\": \"https://t4.ftcdn.net/jpg/00/97/58/97/360_F_97589769_t45CqXyzjz0KXwoBZT9PRaWGHRk5hQqQ.jpg\",\r\n    \"label\": \"cat\",\r\n    \"enableObjectDetection\": true,\r\n    \"dryRun\": true\r\n}",
					"options": {
						"raw": {
							"language": "json"
						}
					}
				},
				"url": {
					"raw": "http://localhost:3000/images",
					"protocol": "http",
					"host": [
						"localhost"
					],
					"port": "3000",
					"path": [
						"images"
					]
				}
			},
			"response": []
		}
	]
}